fca_algorithms_cpp.cp36-win32.pyd
fca_algorithms_cpp-0.3.6.dist-info/LICENSE
fca_algorithms_cpp-0.3.6.dist-info/METADATA
fca_algorithms_cpp-0.3.6.dist-info/WHEEL
fca_algorithms_cpp-0.3.6.dist-info/top_level.txt
fca_algorithms_cpp-0.3.6.dist-info/RECORD
