Metadata-Version: 2.1
Name: fca-algorithms-cpp
Version: 0.3.6
Summary: Cpp implementation of the lib fca_algorithms
Home-page: https://gitlab.com/Lwr/fca_algorithms_cpp
Author: Ramshell
Author-email: ramshellcinox@gmail.com
License: MIT
Classifier: Programming Language :: C++
Classifier: Operating System :: OS Independent
License-File: LICENSE
Requires-Dist: pybind11 >=2.10.4
